pybatchintory/__init__.py
pybatchintory/batch.py
pybatchintory/config/__init__.py
pybatchintory/config/dot_env.py
pybatchintory/config/main.py
pybatchintory/config/settings.py
pybatchintory/logging.py
pybatchintory/main.py
pybatchintory/models.py
pybatchintory/sql/__init__.py
pybatchintory/sql/crud.py
pybatchintory/sql/database.py
pybatchintory/sql/helper.py
pybatchintory/sql/models.py
pybatchintory/sql/reflection.py
pybatchintory/sql/testing.py
pybatchintory/validate.py
pybatchintory-0.0.8.dist-info/LICENSE
pybatchintory-0.0.8.dist-info/METADATA
pybatchintory-0.0.8.dist-info/WHEEL
pybatchintory-0.0.8.dist-info/RECORD
