Metadata-Version: 2.1
Name: pybatchintory
Version: 0.0.8
Summary: Middleware for generating batches of data items enabling incremental processing and backfill scenarios with predictable workloads.
License: MIT
Author: Franz Wöllert
Author-email: franz.woellert@gmail.com
Requires-Python: >=3.7.1,<4.0.0
Classifier: License :: OSI Approved :: MIT License
Classifier: Programming Language :: Python :: 3
Classifier: Programming Language :: Python :: 3.8
Classifier: Programming Language :: Python :: 3.9
Classifier: Programming Language :: Python :: 3.10
Classifier: Programming Language :: Python :: 3.11
Requires-Dist: pandas (>=1.2,<2.0)
Requires-Dist: pydantic (>=1.8,<2.0)
Requires-Dist: sqlalchemy (<1.5) ; python_version >= "3.7" and python_version < "3.8"
Requires-Dist: sqlalchemy (>=2.0,<3.0) ; python_version >= "3.8" and python_version < "4"
